[
    {
        "category": "VISUAL FIELD IS A CONTAINER",
        "sentence": "It's out of my field of vision.",
        "source frame": "Containment",
        "target frame": "Visual_field",
        "source": "",
        "target": "",
        "type": ""
    },
    {
        "category": "MORAL AGENTS ARE NURTURING PARENTS",
        "sentence": "The CEO looks after her employees with motherly kindness.",
        "source frame": "Nurturant parent family",
        "target frame": "Moral action",
        "source": "",
        "target": "",
        "type": ""
    },
    {
        "category": "WINNING AN ELECTION IS WINNING A WAR",
        "sentence": "President Obama won a major victory in November.",
        "source frame": "War",
        "target frame": "Election",
        "source": "victory",
        "target": "",
        "type": ""
    },
    {
        "category": "WINNING AN ELECTION IS WINNING A RACE",
        "sentence": "In the Supervisors race, my candidate came out slightly ahead of his closest rival.",
        "source frame": "Race",
        "target frame": "Election",
        "source": "race",
        "target": "",
        "type": ""
    },
    {
        "category": "MORAL AGENTS ARE NURTURING PARENTS",
        "sentence": "With gentle care and attention, the pastor's congregation will flourish.",
        "source frame": "Nurturant parent family",
        "target frame": "Moral action",
        "source": "care",
        "target": "",
        "type": ""
    },
    {
        "category": "EASE OF ACTION IS EASE OF MOTION ALONG A PATH",
        "sentence": "It is smooth sailing from here on in in the application process.",
        "source frame": "Motion along a path",
        "target frame": "Action",
        "source": "",
        "target": "process",
        "type": ""
    },
    {
        "category": "CAUSED INABILITY TO ACT IS PREVENTION OF MOTION ALONG A PATH",
        "sentence": "He's really gotten hung up at that step in the process.",
        "source frame": "Motion along a path",
        "target frame": "Action",
        "source": "",
        "target": "step/process",
        "type": ""
    },
    {
        "category": "BUSINESS COMPETITION IS COMPETITIVE SPORTS",
        "sentence": "It's Now Apple And Samsung's Game To Lose--Everyone Else Is An Also-Ran",
        "source frame": "Competitive sport",
        "target frame": "Economic competition",
        "source": "",
        "target": "game/lose",
        "type": ""
    }
]